<LensFlareLibrary Name="flares">
 <FlareItem Name="Test.Test" Type="Root" Enable="1" Id="{10992F8D-1F5D-449A-9563-7CBFE7D5BC2D}" Library="flares">
  <Params>
   <Common Size="1" Perspectivefactor="0" DistanceFadingfactor="0" Brightness="0.5" Position="1,1" Tint="1,1,1" Tint.alpha="51" Orbitangle="0" OcclusionInteraction="0" AutoRotation="1" CorrectAspectRatio="1"/>
   <Sensor Sensorimagesizevariationfactor="1" Sensorimagebrightnessvariationfactor="1"/>
   <Transformation Scale="1,1" Translation="0,0" Rotation="0"/>
   <Dynamics Enable="0" TriggerInvert="0" TriggerOffset="0,0" TriggerRange="1" TriggerFalloff="1"/>
   <GlobalSettings EnableOcclusion="1" OcclusionSize="0.02,0.02" Flarefadetime="0.2" Shaftfadetime="1" Affectedbylightcolor="1" Affectedbylightradius="0" AffectedbylightFOV="0" MultiplyColor="1"/>
   <Sensor CustomSensorVariationMap="0" EffectiveSensorSize="0.8"/>
  </Params>
  <FlareItem Name="Test.ghost" Type="Ghost" Enable="1">
   <Params>
    <Common Size="0.3" Perspectivefactor="0" DistanceFadingfactor="1" Brightness="1" Position="1,1" Tint="1,1,1" Tint.alpha="51" Orbitangle="0" OcclusionInteraction="0" AutoRotation="0" CorrectAspectRatio="1"/>
    <Sensor Sensorimagesizevariationfactor="0" Sensorimagebrightnessvariationfactor="0"/>
    <Transformation Scale="1,1" Translation="0,0" Rotation="0"/>
    <Dynamics Enable="0" TriggerInvert="0" TriggerOffset="0,0" TriggerRange="1" TriggerFalloff="1"/>
    <LensGhost Texture="textures/lights/flare01.dds"/>
   </Params>
  </FlareItem>
 </FlareItem>
</LensFlareLibrary>
